text_in_pattern/__init__.py
text_in_pattern/text_in_pattern.py
text_in_pattern-1.0.0.dist-info/licenses/LICENSE
text_in_pattern-1.0.0.dist-info/METADATA
text_in_pattern-1.0.0.dist-info/WHEEL
text_in_pattern-1.0.0.dist-info/top_level.txt
text_in_pattern-1.0.0.dist-info/RECORD
