Metadata-Version: 2.4
Name: text_in_pattern
Version: 1.0.0
Summary: It is a simple Python library that transforms user input text into a stylized pattern using a user-defined symbol.
Home-page: https://github.com/ethicaladarsh/text_in_pattern
Author: Adarsh Kumar
Author-email: ethycaladarsh@example.com
License: MIT
Classifier: Programming Language :: Python :: 3
Classifier: License :: OSI Approved :: MIT License
Classifier: Operating System :: OS Independent
Requires-Python: >=3.6
License-File: LICENSE
Dynamic: author
Dynamic: author-email
Dynamic: classifier
Dynamic: description
Dynamic: description-content-type
Dynamic: home-page
Dynamic: license
Dynamic: license-file
Dynamic: requires-python
Dynamic: summary
